{"type": "FeatureCollection", "features": [{"type": "Feature", "geometry": {"type": "Point", "coordinates": [34.466, 31.502]}, "properties": {"event_id": "SM-ebbfa6bb7a64", "source_event_id": "tg-idfofficial-16392", "date": "2026-02-06", "datetime_utc": "2026-02-06T14:49:23Z", "time_precision": "second", "time_is_estimated": false, "event_kind": "strike", "side": "israel", "weapon": "", "target_type": "Port", "target_military": false, "location": "Gaza City, Gaza", "description": "[IDFofficial] IDF: In Response to the Violation of the Ceasefire Agreement: The IDF Struck Hamas Terror Infrastructure in the Gaza Strip\n\nOver the pas", "details": "", "source_url": "https://t.me/IDFofficial/16392", "video_url": "", "source": "telegram", "telegram_post_id": "IDFofficial/16392"}}]}