{"type": "FeatureCollection", "features": [{"type": "Feature", "geometry": {"type": "Point", "coordinates": [36.211, 34.006]}, "properties": {"event_id": "SM-ff0d43ea0c5e", "source_event_id": "tg-idfofficial-16450", "date": "2026-02-21", "datetime_utc": "2026-02-21T07:46:21Z", "event_kind": "strike", "side": "israel", "weapon": "Missile", "target_type": "Urban area", "target_military": false, "location": "Baalbek, Lebanon", "description": "[IDFofficial] IDF: Yesterday (Friday), the IDF struck and eliminated several terrorists of Hezbollah’s missile array in three different command center", "details": "", "source_url": "https://t.me/IDFofficial/16450", "video_url": "", "source": "telegram", "telegram_post_id": "IDFofficial/16450", "lat_raw": 34.006, "lon_raw": 36.211, "lat": 34.006, "lon": 36.211}}]}