{"type": "FeatureCollection", "features": [{"type": "Feature", "geometry": {"type": "Point", "coordinates": [34.952, 29.558]}, "properties": {"event_id": "SM-8d7aaa6945bd", "source_event_id": "tg-israelwarroom-30", "date": "2026-02-02", "datetime_utc": "2026-02-02T15:11:38Z", "event_kind": "unknown", "side": "iran", "weapon": "Missile", "target_type": "Naval base", "target_military": false, "location": "Eilat, Israel", "description": "[IsraelWarRoom] 🇺🇸🇮🇱💪The USS Delbert D. Black guided missile destroyer conducted a routine maritime exercise with the INS Eilat, an Israeli Navy ", "details": "", "source_url": "https://t.me/IsraelWarRoom/30", "video_url": "", "source": "telegram", "telegram_post_id": "IsraelWarRoom/30", "lat_raw": 29.558, "lon_raw": 34.952, "lat": 29.558, "lon": 34.952}}]}